apiflask/__init__.py
apiflask/app.py
apiflask/blueprint.py
apiflask/commands.py
apiflask/exceptions.py
apiflask/fields.py
apiflask/helpers.py
apiflask/openapi.py
apiflask/openapi_adapters.py
apiflask/py.typed
apiflask/route.py
apiflask/scaffold.py
apiflask/schemas.py
apiflask/security.py
apiflask/settings.py
apiflask/types.py
apiflask/ui_templates.py
apiflask/validators.py
apiflask/views.py
apiflask/schema_adapters/__init__.py
apiflask/schema_adapters/base.py
apiflask/schema_adapters/marshmallow.py
apiflask/schema_adapters/pydantic.py
apiflask/schema_adapters/registry.py
apiflask-3.0.0.dist-info/licenses/LICENSE
apiflask-3.0.0.dist-info/licenses/NOTICE
apiflask-3.0.0.dist-info/METADATA
apiflask-3.0.0.dist-info/WHEEL
apiflask-3.0.0.dist-info/entry_points.txt
apiflask-3.0.0.dist-info/top_level.txt
apiflask-3.0.0.dist-info/RECORD
