Metadata-Version: 2.4
Name: APIFlask
Version: 3.0.0
Summary: A lightweight web API framework based on Flask.
Author-email: Grey Li <withlihui@gmail.com>
License: MIT
Project-URL: Documentation, https://apiflask.com/docs
Project-URL: Changes, https://apiflask.com/changelog
Project-URL: Source Code, https://github.com/apiflask/apiflask
Project-URL: Issue Tracker, https://github.com/apiflask/apiflask/issues
Project-URL: Donate, https://opencollective.com/apiflask
Classifier: Development Status :: 5 - Production/Stable
Classifier: Environment :: Web Environment
Classifier: Framework :: Flask
Classifier: Intended Audience :: Developers
Classifier: Programming Language :: Python :: 3 :: Only
Classifier: Programming Language :: Python :: 3.9
Classifier: Programming Language :: Python :: 3.10
Classifier: Programming Language :: Python :: 3.11
Classifier: Programming Language :: Python :: 3.12
Classifier: Programming Language :: Python :: 3.13
Classifier: Programming Language :: Python :: 3.14
Classifier: License :: OSI Approved :: MIT License
Classifier: Operating System :: OS Independent
Classifier: Topic :: Internet :: WWW/HTTP :: Dynamic Content
Classifier: Topic :: Internet :: WWW/HTTP :: WSGI
Classifier: Topic :: Internet :: WWW/HTTP :: WSGI :: Application
Classifier: Topic :: Software Development :: Libraries :: Application Frameworks
License-File: LICENSE
License-File: NOTICE
Requires-Dist: flask>=2.1.0
Requires-Dist: flask-marshmallow>=1.0.0
Requires-Dist: marshmallow>=3.20
Requires-Dist: webargs>=8.3
Requires-Dist: flask-httpauth>=4.8.0
Requires-Dist: apispec>=6.0.0
Requires-Dist: pydantic[email]>=2.0
Provides-Extra: dotenv
Requires-Dist: python-dotenv; extra == "dotenv"
Provides-Extra: async
Requires-Dist: asgiref>=3.2; extra == "async"
Provides-Extra: yaml
Requires-Dist: pyyaml; extra == "yaml"
Dynamic: license-file
